dynamicdns/__init__.py
dynamicdns/const.py
dynamicdns/providers.py
dynamicdns/py.typed
dynamicdns/updater.py
dynamicdns-0.1.1.dist-info/METADATA
dynamicdns-0.1.1.dist-info/WHEEL
dynamicdns-0.1.1.dist-info/licenses/LICENSE.txt
dynamicdns-0.1.1.dist-info/RECORD
